odoo/addons/pos_session_pay_invoice/README.rst
odoo/addons/pos_session_pay_invoice/__init__.py
odoo/addons/pos_session_pay_invoice/__manifest__.py
odoo/addons/pos_session_pay_invoice/i18n/ca.po
odoo/addons/pos_session_pay_invoice/i18n/es.po
odoo/addons/pos_session_pay_invoice/i18n/pos_session_pay_invoice.pot
odoo/addons/pos_session_pay_invoice/static/description/icon.png
odoo/addons/pos_session_pay_invoice/tests/__init__.py
odoo/addons/pos_session_pay_invoice/tests/test_pay_invoice.py
odoo/addons/pos_session_pay_invoice/views/pos_session.xml
odoo/addons/pos_session_pay_invoice/wizard/__init__.py
odoo/addons/pos_session_pay_invoice/wizard/cash_invoice_in.py
odoo/addons/pos_session_pay_invoice/wizard/cash_invoice_in.xml
odoo/addons/pos_session_pay_invoice/wizard/cash_invoice_out.py
odoo/addons/pos_session_pay_invoice/wizard/cash_invoice_out.xml
odoo11_addon_pos_session_pay_invoice-11.0.1.0.1.dist-info/METADATA
odoo11_addon_pos_session_pay_invoice-11.0.1.0.1.dist-info/WHEEL
odoo11_addon_pos_session_pay_invoice-11.0.1.0.1.dist-info/top_level.txt
odoo11_addon_pos_session_pay_invoice-11.0.1.0.1.dist-info/RECORD
